<?xml version="1.0" encoding="UTF-8"?>
<beans xmlns="http://www.springframework.org/schema/beans"
	xmlns:xsi="http://www.w3.org/2001/XMLSchema-instance"
	xsi:schemaLocation="http://www.springframework.org/schema/beans
    http://www.springframework.org/schema/beans/spring-beans-3.0.xsd">
  		
  		<bean id="itemsClassDoHelp" class="com.whoami.SpringHelper.itemsClassSpringDoHelp">
  				<property name="itemsType" ref="itemsType"></property>
  				<property name="itemsTypeDaoDo" ref="itemsTypeDaoDo"></property>
  		</bean>
  		<bean id="itemsType" class="com.whoami.po.itemsclass"></bean>
  		<bean id="itemsTypeDaoDo" class="com.whoami.daodo.itemsClassDaoDo"></bean>
    </beans>